gpn_zsdparser/__init__.py
gpn_zsdparser/parser.py
gpn_zsdparser/zsd_frame.py
gpn_zsdparser-1.1.dist-info/METADATA
gpn_zsdparser-1.1.dist-info/WHEEL
gpn_zsdparser-1.1.dist-info/top_level.txt
gpn_zsdparser-1.1.dist-info/RECORD
